README.txt
setup.py
ckanext/__init__.py
ckanext/dataapi/__init__.py
ckanext_dataapi.egg-info/PKG-INFO
ckanext_dataapi.egg-info/SOURCES.txt
ckanext_dataapi.egg-info/dependency_links.txt
ckanext_dataapi.egg-info/entry_points.txt
ckanext_dataapi.egg-info/namespace_packages.txt
ckanext_dataapi.egg-info/not-zip-safe
ckanext_dataapi.egg-info/top_level.txt