Metadata-Version: 1.0
Name: ckanext-dataapi
Version: 0.1
Summary: CKAN Extension Data API - preview and access package resources through data transformation proxy service.
Home-page: http://ckan.org/
Author: CKAN Team (Open Knowledge Foundation)
Author-email: ckan@okfn.org
License: mit
Platform: UNKNOWN
